imfpy/__init__.py
imfpy/retrievals.py
imfpy/searches.py
imfpy/tools.py
imfpy-0.0.2.dist-info/LICENSE
imfpy-0.0.2.dist-info/WHEEL
imfpy-0.0.2.dist-info/METADATA
imfpy-0.0.2.dist-info/RECORD
