Metadata-Version: 2.1
Name: imfpy
Version: 0.0.2
Summary: A client for interacting with the IMF's JSON RESTful API with Python!
Home-page: https://github.com/ltk2118/imfpy
License: MIT
Keywords: Trade,IMF,DOTS
Author: Liam Tay Kearney
Requires-Python: >=3.7,<4.0
Classifier: License :: OSI Approved :: MIT License
Classifier: Programming Language :: Python :: 3
Classifier: Programming Language :: Python :: 3.7
Classifier: Programming Language :: Python :: 3.8
Classifier: Programming Language :: Python :: 3.9
Requires-Dist: matplotlib (>=3.2.2,<4.0.0)
Requires-Dist: pandas (>=1.1.3,<2.0.0)
Requires-Dist: requests (>=2.19.0,<3.0.0)
